py_dto/__init__.py
py_dto-1.1.0.dist-info/LICENSE.txt
py_dto-1.1.0.dist-info/METADATA
py_dto-1.1.0.dist-info/WHEEL
py_dto-1.1.0.dist-info/top_level.txt
py_dto-1.1.0.dist-info/RECORD
