Metadata-Version: 2.1
Name: py_dto
Version: 1.1.0
Summary: data transfer objects with Python
Home-page: https://github.com/rogervila/py_dto
Download-URL: https://github.com/rogervila/py_dto/archive/1.1.0.tar.gz
Author: Roger Vilà
Author-email: rogervila@me.com
License: MIT
Keywords: python data transfer objects,data transfer objects,python dto,dto
Classifier: Development Status :: 5 - Production/Stable
Classifier: Intended Audience :: Developers
Classifier: Topic :: Software Development :: Build Tools
Classifier: License :: OSI Approved :: MIT License
Classifier: Programming Language :: Python :: 3.9
License-File: LICENSE.txt
Requires-Dist: runtype >=0.5.0
